boq/__init__.py
boq/cli.py
boq/config.py
boq/core.py
boq/defaults.toml
boq-0.0.4.dist-info/METADATA
boq-0.0.4.dist-info/WHEEL
boq-0.0.4.dist-info/entry_points.txt
boq-0.0.4.dist-info/RECORD
