Metadata-Version: 2.4
Name: boq
Version: 0.0.4
Summary: Safe YOLO with AI code tools: universal isolated development environment using kernel overlayfs
License-Expression: MIT
Keywords: container,development,overlayfs,podman,sandbox
Classifier: Development Status :: 4 - Beta
Classifier: Environment :: Console
Classifier: Intended Audience :: Developers
Classifier: License :: OSI Approved :: MIT License
Classifier: Operating System :: POSIX :: Linux
Classifier: Programming Language :: Python :: 3.11
Classifier: Programming Language :: Python :: 3.12
Classifier: Topic :: Software Development
Classifier: Topic :: System :: Systems Administration
Requires-Python: >=3.11
